scop2sdfg/__init__.py
scop2sdfg/cli/__init__.py
scop2sdfg/codegen/__init__.py
scop2sdfg/codegen/generator.py
scop2sdfg/codegen/analysis/__init__.py
scop2sdfg/codegen/isl/__init__.py
scop2sdfg/scop/__init__.py
scop2sdfg/scop/ast.py
scop2sdfg/scop/scop.py
scop2sdfg/scop/types.py
scop2sdfg/scop/undefined_value.py
scop2sdfg/scop/value.py
scop2sdfg/scop/analysis/__init__.py
scop2sdfg/scop/analysis/undefined_access_to_indirection.py
scop2sdfg/scop/analysis/value_propagation.py
scop2sdfg/scop/computation/__init__.py
scop2sdfg/scop/computation/access.py
scop2sdfg/scop/computation/computation.py
scop2sdfg/scop/computation/indirection.py
scop2sdfg/scop/symbols/__init__.py
scop2sdfg/scop/symbols/constant.py
scop2sdfg/scop/symbols/loop.py
scop2sdfg/scop/symbols/memref.py
scop2sdfg/scop/symbols/parameter.py
scop2sdfg-0.0.1.dist-info/LICENSE
scop2sdfg-0.0.1.dist-info/METADATA
scop2sdfg-0.0.1.dist-info/WHEEL
scop2sdfg-0.0.1.dist-info/entry_points.txt
scop2sdfg-0.0.1.dist-info/top_level.txt
scop2sdfg-0.0.1.dist-info/RECORD
